wfm_checker/__init__.py
wfm_checker/api.py
wfm_checker/cli.py
wfm_checker/constants.py
wfm_checker/exporters.py
wfm_checker/normalizers.py
wfm_checker/parsers.py
wfm_checker-0.1.0.dist-info/METADATA
wfm_checker-0.1.0.dist-info/WHEEL
wfm_checker-0.1.0.dist-info/entry_points.txt
wfm_checker-0.1.0.dist-info/licenses/LICENSE
wfm_checker-0.1.0.dist-info/RECORD
